{
  "diary": [
    {
      "id": 1774306331379,
      "source": "paper",
      "ticker": "KO",
      "date": "22 de diciembre de 2025",
      "type": "sell",
      "price": 70.21,
      "stop": null,
      "target": null,
      "emotion": "",
      "reason": "",
      "lesson": "Ya hab铆a ganado m谩s de un 10% que para mi es la decisi贸n de vender y salir. No ser avaricioso. El rsi estaba en 49 que esta bien y parec铆a que el valor estaba tocando el suelo sobre la media y podr铆a rebotar pero mejor vender, recoger ganancias y acert茅 ",
      "result30": 2.4,
      "result90": 6.5,
      "correct": false,
      "indicators": {
        "rsi": 49,
        "hist": -0.07,
        "score": 3,
        "golden": true
      },
      "feedback": "芒職聽茂赂聫 El mercado se qued脙鲁 lateral tras tu salida. Decisi脙鲁n defensiva, no necesariamente incorrecta.",
      "createdAt": "2026-03-23T22:52:11.379Z"
    },
    {
      "id": 1774306127964,
      "source": "paper",
      "ticker": "BAC",
      "date": "22 de diciembre de 2025",
      "type": "sell",
      "price": 55.88,
      "stop": null,
      "target": null,
      "emotion": "",
      "reason": "",
      "lesson": "Ya hab脙颅a ganado un 12% con esa acci脙鲁n que por encima de 10% ya considero suficiente. Hab脙颅a algo de sobrecompra con el RSI a 65. La acci脙鲁n ven脙颅a de una buena subida y todo eso me hizo vender y cobrar las ganancias ",
      "result30": -6.1,
      "result90": -15.6,
      "correct": true,
      "indicators": {
        "rsi": 67,
        "hist": 0.095,
        "score": 3,
        "golden": true
      },
      "feedback": "脙垄脗聹脗聟 Buena decisi脙聝脗鲁n salir. La acci脙聝脗鲁n cay脙聝脗鲁 -6.1% despu脙聝脗漏s 脙垄脗聙脗聰 cortaste las p脙聝脗漏rdidas a tiempo.",
      "createdAt": "2026-03-23T22:48:47.964Z"
    },
    {
      "id": 1774305924833,
      "source": "paper",
      "ticker": "MS",
      "date": "22 de diciembre de 2025",
      "type": "wait",
      "price": 179.76,
      "stop": null,
      "target": null,
      "emotion": "",
      "reason": "",
      "lesson": "El contexto era bueno pero hab脙聝脗颅a algo de sobrecompra con el RSI a 65 que me echo para atr脙聝脗隆s. Adem脙聝脗隆s el valor ven脙聝脗颅a de una buena subida sobre la media m脙聝脗鲁vil y era probable que ya le quedara poco recorrido ",
      "result30": 1.8,
      "result90": -10.2,
      "correct": true,
      "indicators": {
        "rsi": 65,
        "hist": -0.394,
        "score": 2,
        "golden": true
      },
      "feedback": "脙聝脗垄脙聜脗聹脙聜脗聟 Sin tendencia clara, esperar fue lo correcto. No necesitas estar siempre en el mercado.",
      "createdAt": "2026-03-23T22:45:24.833Z"
    },
    {
      "id": 1774305738436,
      "source": "paper",
      "ticker": "NEE",
      "date": "22 de septiembre de 2025",
      "type": "buy",
      "price": 72.35,
      "stop": null,
      "target": null,
      "emotion": "",
      "reason": "",
      "lesson": "Identificar los patrones. Leer el contexto es importante. Poner un stop loss conservador siempre es la mejor opci脙聝脗聝脙聜脗聝脙聝脗聜脙聜脗鲁n ",
      "result30": 17.2,
      "result90": 12.4,
      "correct": true,
      "indicators": {
        "rsi": 52,
        "hist": 0.136,
        "score": 2,
        "golden": true
      },
      "feedback": "脙聝脗聝脙聜脗聝脙聝脗聜脙聜脗垄脙聝脗聝脙聜脗聜脙聝脗聜脙聜脗聹脙聝脗聝脙聜脗聜脙聝脗聜脙聜脗聟 Entrada correcta. La acci脙聝脗聝脙聜脗聝脙聝脗聜脙聜脗聝脙聝脗聝脙聜脗聜脙聝脗聜脙聜脗鲁n subi脙聝脗聝脙聜脗聝脙聝脗聜脙聜脗聝脙聝脗聝脙聜脗聜脙聝脗聜脙聜脗鲁 17.2% en 30 d脙聝脗聝脙聜脗聝脙聝脗聜脙聜脗聝脙聝脗聝脙聜脗聜脙聝脗聜脙聜脗颅as. Identificaste bien la oportunidad.",
      "createdAt": "2026-03-23T22:42:18.436Z"
    }
  ],
  "guide": {
    "read-aprende": "2026-03-23T22:40:16.930Z"
  },
  "updatedAt": "2026-03-23T23:02:55.285Z"
}